package com.google.android.gms.measurement.internal;

import android.database.sqlite.*;
import android.content.*;
import com.google.android.gms.common.util.*;
import android.os.*;
import java.util.*;
import com.google.android.gms.common.internal.safeparcel.*;

public final class zzal extends zzf
{
    private final zzam zzalq;
    private boolean zzalr;
    
    zzal(final zzbt zzbt) {
        super(zzbt);
        this.zzalq = new zzam(this, this.getContext(), "google_app_measurement_local.db");
    }
    
    private final SQLiteDatabase getWritableDatabase() throws SQLiteException {
        if (this.zzalr) {
            return null;
        }
        final SQLiteDatabase writableDatabase = this.zzalq.getWritableDatabase();
        if (writableDatabase == null) {
            this.zzalr = true;
            return null;
        }
        return writableDatabase;
    }
    
    private final boolean zza(final int p0, final byte[] p1) {
        // 
        // This method could not be decompiled.
        // 
        // Original Bytecode:
        // 
        //     1: invokevirtual   com/google/android/gms/measurement/internal/zzco.zzgb:()V
        //     4: aload_0        
        //     5: invokevirtual   com/google/android/gms/measurement/internal/zzco.zzaf:()V
        //     8: aload_0        
        //     9: getfield        com/google/android/gms/measurement/internal/zzal.zzalr:Z
        //    12: ifeq            17
        //    15: iconst_0       
        //    16: ireturn        
        //    17: new             Landroid/content/ContentValues;
        //    20: dup            
        //    21: invokespecial   android/content/ContentValues.<init>:()V
        //    24: astore          13
        //    26: aload           13
        //    28: ldc             "type"
        //    30: iload_1        
        //    31: invokestatic    java/lang/Integer.valueOf:(I)Ljava/lang/Integer;
        //    34: invokevirtual   android/content/ContentValues.put:(Ljava/lang/String;Ljava/lang/Integer;)V
        //    37: aload           13
        //    39: ldc             "entry"
        //    41: aload_2        
        //    42: invokevirtual   android/content/ContentValues.put:(Ljava/lang/String;[B)V
        //    45: iconst_0       
        //    46: istore          4
        //    48: iconst_5       
        //    49: istore_3       
        //    50: iload           4
        //    52: iconst_5       
        //    53: if_icmpge       717
        //    56: aconst_null    
        //    57: astore          9
        //    59: aconst_null    
        //    60: astore          11
        //    62: aload_0        
        //    63: invokespecial   com/google/android/gms/measurement/internal/zzal.getWritableDatabase:()Landroid/database/sqlite/SQLiteDatabase;
        //    66: astore_2       
        //    67: aload_2        
        //    68: ifnonnull       128
        //    71: aload_0        
        //    72: iconst_1       
        //    73: putfield        com/google/android/gms/measurement/internal/zzal.zzalr:Z
        //    76: aload_2        
        //    77: ifnull          84
        //    80: aload_2        
        //    81: invokevirtual   android/database/sqlite/SQLiteDatabase.close:()V
        //    84: iconst_0       
        //    85: ireturn        
        //    86: astore          10
        //    88: aconst_null    
        //    89: astore          11
        //    91: aload_2        
        //    92: astore          9
        //    94: aload           10
        //    96: astore_2       
        //    97: aload           11
        //    99: astore          10
        //   101: goto            693
        //   104: astore          9
        //   106: aload_2        
        //   107: astore          10
        //   109: aload           9
        //   111: astore_2       
        //   112: aload           10
        //   114: astore          9
        //   116: aload           11
        //   118: astore          10
        //   120: goto            431
        //   123: astore          10
        //   125: goto            617
        //   128: aload_2        
        //   129: invokevirtual   android/database/sqlite/SQLiteDatabase.beginTransaction:()V
        //   132: lconst_0       
        //   133: lstore          7
        //   135: aload_2        
        //   136: ldc             "select count(1) from messages"
        //   138: aconst_null    
        //   139: invokevirtual   android/database/sqlite/SQLiteDatabase.rawQuery:(Ljava/lang/String;[Ljava/lang/String;)Landroid/database/Cursor;
        //   142: astore          10
        //   144: lload           7
        //   146: lstore          5
        //   148: aload           10
        //   150: ifnull          180
        //   153: lload           7
        //   155: lstore          5
        //   157: aload           10
        //   159: invokeinterface android/database/Cursor.moveToFirst:()Z
        //   164: ifeq            180
        //   167: aload           10
        //   169: iconst_0       
        //   170: invokeinterface android/database/Cursor.getLong:(I)J
        //   175: lstore          5
        //   177: goto            180
        //   180: lload           5
        //   182: ldc2_w          100000
        //   185: lcmp           
        //   186: iflt            294
        //   189: aload_0        
        //   190: invokevirtual   com/google/android/gms/measurement/internal/zzco.zzgo:()Lcom/google/android/gms/measurement/internal/zzap;
        //   193: invokevirtual   com/google/android/gms/measurement/internal/zzap.zzjd:()Lcom/google/android/gms/measurement/internal/zzar;
        //   196: ldc             "Data loss, local db full"
        //   198: invokevirtual   com/google/android/gms/measurement/internal/zzar.zzbx:(Ljava/lang/String;)V
        //   201: ldc2_w          100000
        //   204: lload           5
        //   206: lsub           
        //   207: lconst_1       
        //   208: ladd           
        //   209: lstore          5
        //   211: aload_2        
        //   212: ldc             "messages"
        //   214: ldc             "rowid in (select rowid from messages order by rowid asc limit ?)"
        //   216: iconst_1       
        //   217: anewarray       Ljava/lang/String;
        //   220: dup            
        //   221: iconst_0       
        //   222: lload           5
        //   224: invokestatic    java/lang/Long.toString:(J)Ljava/lang/String;
        //   227: aastore        
        //   228: invokevirtual   android/database/sqlite/SQLiteDatabase.delete:(Ljava/lang/String;Ljava/lang/String;[Ljava/lang/String;)I
        //   231: i2l            
        //   232: lstore          7
        //   234: lload           7
        //   236: lload           5
        //   238: lcmp           
        //   239: ifeq            294
        //   242: aload_0        
        //   243: invokevirtual   com/google/android/gms/measurement/internal/zzco.zzgo:()Lcom/google/android/gms/measurement/internal/zzap;
        //   246: invokevirtual   com/google/android/gms/measurement/internal/zzap.zzjd:()Lcom/google/android/gms/measurement/internal/zzar;
        //   249: astore          11
        //   251: aload_2        
        //   252: astore          9
        //   254: aload           11
        //   256: ldc             "Different delete count than expected in local db. expected, received, difference"
        //   258: lload           5
        //   260: invokestatic    java/lang/Long.valueOf:(J)Ljava/lang/Long;
        //   263: lload           7
        //   265: invokestatic    java/lang/Long.valueOf:(J)Ljava/lang/Long;
        //   268: lload           5
        //   270: lload           7
        //   272: lsub           
        //   273: invokestatic    java/lang/Long.valueOf:(J)Ljava/lang/Long;
        //   276: invokevirtual   com/google/android/gms/measurement/internal/zzar.zzd:(Ljava/lang/String;Ljava/lang/Object;Ljava/lang/Object;Ljava/lang/Object;)V
        //   279: goto            294
        //   282: astore_2       
        //   283: goto            360
        //   286: astore_2       
        //   287: goto            369
        //   290: astore_2       
        //   291: goto            389
        //   294: aload_2        
        //   295: ldc             "messages"
        //   297: aconst_null    
        //   298: aload           13
        //   300: invokevirtual   android/database/sqlite/SQLiteDatabase.insertOrThrow:(Ljava/lang/String;Ljava/lang/String;Landroid/content/ContentValues;)J
        //   303: pop2           
        //   304: aload_2        
        //   305: invokevirtual   android/database/sqlite/SQLiteDatabase.setTransactionSuccessful:()V
        //   308: aload_2        
        //   309: invokevirtual   android/database/sqlite/SQLiteDatabase.endTransaction:()V
        //   312: aload           10
        //   314: ifnull          324
        //   317: aload           10
        //   319: invokeinterface android/database/Cursor.close:()V
        //   324: aload_2        
        //   325: ifnull          332
        //   328: aload_2        
        //   329: invokevirtual   android/database/sqlite/SQLiteDatabase.close:()V
        //   332: iconst_1       
        //   333: ireturn        
        //   334: astore          11
        //   336: goto            354
        //   339: astore          11
        //   341: goto            363
        //   344: astore          9
        //   346: goto            376
        //   349: astore          11
        //   351: goto            383
        //   354: aload_2        
        //   355: astore          9
        //   357: aload           11
        //   359: astore_2       
        //   360: goto            553
        //   363: aload_2        
        //   364: astore          9
        //   366: aload           11
        //   368: astore_2       
        //   369: goto            431
        //   372: astore_2       
        //   373: aload           9
        //   375: astore_2       
        //   376: aload           10
        //   378: astore          9
        //   380: goto            562
        //   383: aload_2        
        //   384: astore          9
        //   386: aload           11
        //   388: astore_2       
        //   389: aload           10
        //   391: astore          11
        //   393: aload_2        
        //   394: astore          10
        //   396: aload           9
        //   398: astore_2       
        //   399: aload           11
        //   401: astore          9
        //   403: goto            617
        //   406: astore          11
        //   408: aconst_null    
        //   409: astore          10
        //   411: aload_2        
        //   412: astore          9
        //   414: aload           11
        //   416: astore_2       
        //   417: goto            693
        //   420: astore          11
        //   422: aconst_null    
        //   423: astore          10
        //   425: aload_2        
        //   426: astore          9
        //   428: aload           11
        //   430: astore_2       
        //   431: aload_2        
        //   432: astore          11
        //   434: aload           9
        //   436: astore_2       
        //   437: aload           10
        //   439: astore          9
        //   441: goto            483
        //   444: astore          9
        //   446: aconst_null    
        //   447: astore          9
        //   449: goto            562
        //   452: astore          10
        //   454: aconst_null    
        //   455: astore          9
        //   457: goto            617
        //   460: astore_2       
        //   461: aconst_null    
        //   462: astore          10
        //   464: aload           10
        //   466: astore          9
        //   468: goto            693
        //   471: astore          10
        //   473: aconst_null    
        //   474: astore          9
        //   476: aload           9
        //   478: astore_2       
        //   479: aload           10
        //   481: astore          11
        //   483: aload_2        
        //   484: ifnull          501
        //   487: aload_2        
        //   488: invokevirtual   android/database/sqlite/SQLiteDatabase.inTransaction:()Z
        //   491: ifeq            501
        //   494: aload_2        
        //   495: invokevirtual   android/database/sqlite/SQLiteDatabase.endTransaction:()V
        //   498: goto            501
        //   501: aload_0        
        //   502: invokevirtual   com/google/android/gms/measurement/internal/zzco.zzgo:()Lcom/google/android/gms/measurement/internal/zzap;
        //   505: invokevirtual   com/google/android/gms/measurement/internal/zzap.zzjd:()Lcom/google/android/gms/measurement/internal/zzar;
        //   508: ldc             "Error writing entry to local database"
        //   510: aload           11
        //   512: invokevirtual   com/google/android/gms/measurement/internal/zzar.zzg:(Ljava/lang/String;Ljava/lang/Object;)V
        //   515: aload_0        
        //   516: iconst_1       
        //   517: putfield        com/google/android/gms/measurement/internal/zzal.zzalr:Z
        //   520: aload           9
        //   522: ifnull          532
        //   525: aload           9
        //   527: invokeinterface android/database/Cursor.close:()V
        //   532: iload_3        
        //   533: istore_1       
        //   534: aload_2        
        //   535: ifnull          673
        //   538: iload_3        
        //   539: istore_1       
        //   540: goto            603
        //   543: aload           9
        //   545: astore          10
        //   547: aload_2        
        //   548: astore          9
        //   550: aload           11
        //   552: astore_2       
        //   553: goto            693
        //   556: astore_2       
        //   557: aconst_null    
        //   558: astore_2       
        //   559: aload_2        
        //   560: astore          9
        //   562: iload_3        
        //   563: i2l            
        //   564: lstore          5
        //   566: aload_2        
        //   567: astore          11
        //   569: aload           9
        //   571: astore          12
        //   573: lload           5
        //   575: invokestatic    android/os/SystemClock.sleep:(J)V
        //   578: iload_3        
        //   579: bipush          20
        //   581: iadd           
        //   582: istore_3       
        //   583: aload           9
        //   585: ifnull          595
        //   588: aload           9
        //   590: invokeinterface android/database/Cursor.close:()V
        //   595: iload_3        
        //   596: istore_1       
        //   597: aload_2        
        //   598: ifnull          673
        //   601: iload_3        
        //   602: istore_1       
        //   603: aload_2        
        //   604: invokevirtual   android/database/sqlite/SQLiteDatabase.close:()V
        //   607: goto            673
        //   610: astore          10
        //   612: aconst_null    
        //   613: astore_2       
        //   614: aload_2        
        //   615: astore          9
        //   617: aload_2        
        //   618: astore          11
        //   620: aload           9
        //   622: astore          12
        //   624: aload_0        
        //   625: invokevirtual   com/google/android/gms/measurement/internal/zzco.zzgo:()Lcom/google/android/gms/measurement/internal/zzap;
        //   628: invokevirtual   com/google/android/gms/measurement/internal/zzap.zzjd:()Lcom/google/android/gms/measurement/internal/zzar;
        //   631: ldc             "Error writing entry to local database"
        //   633: aload           10
        //   635: invokevirtual   com/google/android/gms/measurement/internal/zzar.zzg:(Ljava/lang/String;Ljava/lang/Object;)V
        //   638: aload_2        
        //   639: astore          11
        //   641: aload           9
        //   643: astore          12
        //   645: aload_0        
        //   646: iconst_1       
        //   647: putfield        com/google/android/gms/measurement/internal/zzal.zzalr:Z
        //   650: aload           9
        //   652: ifnull          662
        //   655: aload           9
        //   657: invokeinterface android/database/Cursor.close:()V
        //   662: iload_3        
        //   663: istore_1       
        //   664: aload_2        
        //   665: ifnull          673
        //   668: iload_3        
        //   669: istore_1       
        //   670: goto            603
        //   673: iload           4
        //   675: iconst_1       
        //   676: iadd           
        //   677: istore          4
        //   679: iload_1        
        //   680: istore_3       
        //   681: goto            50
        //   684: astore_2       
        //   685: aload           12
        //   687: astore          10
        //   689: aload           11
        //   691: astore          9
        //   693: aload           10
        //   695: ifnull          705
        //   698: aload           10
        //   700: invokeinterface android/database/Cursor.close:()V
        //   705: aload           9
        //   707: ifnull          715
        //   710: aload           9
        //   712: invokevirtual   android/database/sqlite/SQLiteDatabase.close:()V
        //   715: aload_2        
        //   716: athrow         
        //   717: aload_0        
        //   718: invokevirtual   com/google/android/gms/measurement/internal/zzco.zzgo:()Lcom/google/android/gms/measurement/internal/zzap;
        //   721: invokevirtual   com/google/android/gms/measurement/internal/zzap.zzjg:()Lcom/google/android/gms/measurement/internal/zzar;
        //   724: ldc             "Failed to write entry to local database"
        //   726: invokevirtual   com/google/android/gms/measurement/internal/zzar.zzbx:(Ljava/lang/String;)V
        //   729: iconst_0       
        //   730: ireturn        
        //   731: astore          9
        //   733: aload_2        
        //   734: astore          11
        //   736: aload           9
        //   738: astore_2       
        //   739: aload           11
        //   741: astore          9
        //   743: goto            360
        //   746: astore          9
        //   748: aload_2        
        //   749: astore          11
        //   751: aload           9
        //   753: astore_2       
        //   754: aload           11
        //   756: astore          9
        //   758: goto            369
        //   761: astore          9
        //   763: goto            376
        //   766: astore          9
        //   768: aload_2        
        //   769: astore          11
        //   771: aload           9
        //   773: astore_2       
        //   774: aload           11
        //   776: astore          9
        //   778: goto            389
        //   781: astore          11
        //   783: goto            543
        //    Exceptions:
        //  Try           Handler
        //  Start  End    Start  End    Type                                                   
        //  -----  -----  -----  -----  -------------------------------------------------------
        //  62     67     610    617    Landroid/database/sqlite/SQLiteFullException;
        //  62     67     556    562    Landroid/database/sqlite/SQLiteDatabaseLockedException;
        //  62     67     471    483    Landroid/database/sqlite/SQLiteException;
        //  62     67     460    471    Any
        //  71     76     123    128    Landroid/database/sqlite/SQLiteFullException;
        //  71     76     444    452    Landroid/database/sqlite/SQLiteDatabaseLockedException;
        //  71     76     104    123    Landroid/database/sqlite/SQLiteException;
        //  71     76     86     104    Any
        //  128    132    452    460    Landroid/database/sqlite/SQLiteFullException;
        //  128    132    444    452    Landroid/database/sqlite/SQLiteDatabaseLockedException;
        //  128    132    420    431    Landroid/database/sqlite/SQLiteException;
        //  128    132    406    420    Any
        //  135    144    452    460    Landroid/database/sqlite/SQLiteFullException;
        //  135    144    444    452    Landroid/database/sqlite/SQLiteDatabaseLockedException;
        //  135    144    420    431    Landroid/database/sqlite/SQLiteException;
        //  135    144    406    420    Any
        //  157    177    766    781    Landroid/database/sqlite/SQLiteFullException;
        //  157    177    761    766    Landroid/database/sqlite/SQLiteDatabaseLockedException;
        //  157    177    746    761    Landroid/database/sqlite/SQLiteException;
        //  157    177    731    746    Any
        //  189    201    766    781    Landroid/database/sqlite/SQLiteFullException;
        //  189    201    761    766    Landroid/database/sqlite/SQLiteDatabaseLockedException;
        //  189    201    746    761    Landroid/database/sqlite/SQLiteException;
        //  189    201    731    746    Any
        //  211    234    766    781    Landroid/database/sqlite/SQLiteFullException;
        //  211    234    761    766    Landroid/database/sqlite/SQLiteDatabaseLockedException;
        //  211    234    746    761    Landroid/database/sqlite/SQLiteException;
        //  211    234    731    746    Any
        //  242    251    766    781    Landroid/database/sqlite/SQLiteFullException;
        //  242    251    761    766    Landroid/database/sqlite/SQLiteDatabaseLockedException;
        //  242    251    746    761    Landroid/database/sqlite/SQLiteException;
        //  242    251    731    746    Any
        //  254    279    290    294    Landroid/database/sqlite/SQLiteFullException;
        //  254    279    372    376    Landroid/database/sqlite/SQLiteDatabaseLockedException;
        //  254    279    286    290    Landroid/database/sqlite/SQLiteException;
        //  254    279    282    286    Any
        //  294    312    349    354    Landroid/database/sqlite/SQLiteFullException;
        //  294    312    344    349    Landroid/database/sqlite/SQLiteDatabaseLockedException;
        //  294    312    339    344    Landroid/database/sqlite/SQLiteException;
        //  294    312    334    339    Any
        //  487    498    781    553    Any
        //  501    520    781    553    Any
        //  573    578    684    693    Any
        //  624    638    684    693    Any
        //  645    650    684    693    Any
        // 
        // The error that occurred was:
        // 
        // java.lang.IndexOutOfBoundsException: Index: 404, Size: 404
        //     at java.util.ArrayList.rangeCheck(Unknown Source)
        //     at java.util.ArrayList.get(Unknown Source)
        //     at com.strobel.decompiler.ast.AstBuilder.convertToAst(AstBuilder.java:3321)
        //     at com.strobel.decompiler.ast.AstBuilder.build(AstBuilder.java:113)
        //     at com.strobel.decompiler.languages.java.ast.AstMethodBodyBuilder.createMethodBody(AstMethodBodyBuilder.java:210)
        //     at com.strobel.decompiler.languages.java.ast.AstMethodBodyBuilder.createMethodBody(AstMethodBodyBuilder.java:99)
        //     at com.strobel.decompiler.languages.java.ast.AstBuilder.createMethodBody(AstBuilder.java:782)
        //     at com.strobel.decompiler.languages.java.ast.AstBuilder.createMethod(AstBuilder.java:675)
        //     at com.strobel.decompiler.languages.java.ast.AstBuilder.addTypeMembers(AstBuilder.java:552)
        //     at com.strobel.decompiler.languages.java.ast.AstBuilder.createTypeCore(AstBuilder.java:519)
        //     at com.strobel.decompiler.languages.java.ast.AstBuilder.createTypeNoCache(AstBuilder.java:161)
        //     at com.strobel.decompiler.languages.java.ast.AstBuilder.createType(AstBuilder.java:150)
        //     at com.strobel.decompiler.languages.java.ast.AstBuilder.addType(AstBuilder.java:125)
        //     at com.strobel.decompiler.languages.java.JavaLanguage.buildAst(JavaLanguage.java:71)
        //     at com.strobel.decompiler.languages.java.JavaLanguage.decompileType(JavaLanguage.java:59)
        //     at us.deathmarine.luyten.FileSaver.doSaveJarDecompiled(FileSaver.java:192)
        //     at us.deathmarine.luyten.FileSaver.access$300(FileSaver.java:45)
        //     at us.deathmarine.luyten.FileSaver$4.run(FileSaver.java:112)
        //     at java.lang.Thread.run(Unknown Source)
        // 
        throw new IllegalStateException("An error occurred while decompiling this method.");
    }
    
    public final void resetAnalyticsData() {
        this.zzgb();
        this.zzaf();
        try {
            final int n = this.getWritableDatabase().delete("messages", (String)null, (String[])null) + 0;
            if (n > 0) {
                this.zzgo().zzjl().zzg("Reset local analytics data. records", n);
            }
        }
        catch (SQLiteException ex) {
            this.zzgo().zzjd().zzg("Error resetting local analytics data. error", ex);
        }
    }
    
    public final boolean zza(final zzad zzad) {
        final Parcel obtain = Parcel.obtain();
        zzad.writeToParcel(obtain, 0);
        final byte[] marshall = obtain.marshall();
        obtain.recycle();
        if (marshall.length > 131072) {
            this.zzgo().zzjg().zzbx("Event is too long for local database. Sending event directly to service");
            return false;
        }
        return this.zza(0, marshall);
    }
    
    public final boolean zza(final zzfh zzfh) {
        final Parcel obtain = Parcel.obtain();
        zzfh.writeToParcel(obtain, 0);
        final byte[] marshall = obtain.marshall();
        obtain.recycle();
        if (marshall.length > 131072) {
            this.zzgo().zzjg().zzbx("User property too long for local database. Sending directly to service");
            return false;
        }
        return this.zza(1, marshall);
    }
    
    public final boolean zzc(final zzl zzl) {
        this.zzgm();
        final byte[] zza = zzfk.zza((Parcelable)zzl);
        if (zza.length > 131072) {
            this.zzgo().zzjg().zzbx("Conditional user property too long for local database. Sending directly to service");
            return false;
        }
        return this.zza(2, zza);
    }
    
    @Override
    protected final boolean zzgt() {
        return false;
    }
    
    public final List<AbstractSafeParcelable> zzr(final int p0) {
        // 
        // This method could not be decompiled.
        // 
        // Original Bytecode:
        // 
        //     1: invokevirtual   com/google/android/gms/measurement/internal/zzco.zzaf:()V
        //     4: aload_0        
        //     5: invokevirtual   com/google/android/gms/measurement/internal/zzco.zzgb:()V
        //     8: aload_0        
        //     9: getfield        com/google/android/gms/measurement/internal/zzal.zzalr:Z
        //    12: ifeq            17
        //    15: aconst_null    
        //    16: areturn        
        //    17: new             Ljava/util/ArrayList;
        //    20: dup            
        //    21: invokespecial   java/util/ArrayList.<init>:()V
        //    24: astore          13
        //    26: aload_0        
        //    27: invokevirtual   com/google/android/gms/measurement/internal/zzco.getContext:()Landroid/content/Context;
        //    30: ldc             "google_app_measurement_local.db"
        //    32: invokevirtual   android/content/Context.getDatabasePath:(Ljava/lang/String;)Ljava/io/File;
        //    35: invokevirtual   java/io/File.exists:()Z
        //    38: ifne            44
        //    41: aload           13
        //    43: areturn        
        //    44: iconst_0       
        //    45: istore_3       
        //    46: iconst_5       
        //    47: istore_1       
        //    48: aconst_null    
        //    49: astore          12
        //    51: aconst_null    
        //    52: astore          8
        //    54: iload_3        
        //    55: iconst_5       
        //    56: if_icmpge       1197
        //    59: aload_0        
        //    60: invokespecial   com/google/android/gms/measurement/internal/zzal.getWritableDatabase:()Landroid/database/sqlite/SQLiteDatabase;
        //    63: astore          10
        //    65: aload           10
        //    67: astore          9
        //    69: aload           9
        //    71: ifnonnull       123
        //    74: aload           9
        //    76: astore          11
        //    78: aload_0        
        //    79: iconst_1       
        //    80: putfield        com/google/android/gms/measurement/internal/zzal.zzalr:Z
        //    83: aload           9
        //    85: ifnull          93
        //    88: aload           9
        //    90: invokevirtual   android/database/sqlite/SQLiteDatabase.close:()V
        //    93: aconst_null    
        //    94: areturn        
        //    95: aload           12
        //    97: astore          10
        //    99: goto            1172
        //   102: astore          12
        //   104: aconst_null    
        //   105: astore          10
        //   107: aload           9
        //   109: astore          8
        //   111: aload           10
        //   113: astore          9
        //   115: goto            937
        //   118: astore          10
        //   120: goto            1096
        //   123: aload           9
        //   125: invokevirtual   android/database/sqlite/SQLiteDatabase.beginTransaction:()V
        //   128: bipush          100
        //   130: invokestatic    java/lang/Integer.toString:(I)Ljava/lang/String;
        //   133: astore          11
        //   135: aload           9
        //   137: astore          8
        //   139: aload           9
        //   141: ldc             "messages"
        //   143: iconst_3       
        //   144: anewarray       Ljava/lang/String;
        //   147: dup            
        //   148: iconst_0       
        //   149: ldc_w           "rowid"
        //   152: aastore        
        //   153: dup            
        //   154: iconst_1       
        //   155: ldc             "type"
        //   157: aastore        
        //   158: dup            
        //   159: iconst_2       
        //   160: ldc             "entry"
        //   162: aastore        
        //   163: aconst_null    
        //   164: aconst_null    
        //   165: aconst_null    
        //   166: aconst_null    
        //   167: ldc_w           "rowid asc"
        //   170: aload           11
        //   172: invokevirtual   android/database/sqlite/SQLiteDatabase.query:(Ljava/lang/String;[Ljava/lang/String;Ljava/lang/String;[Ljava/lang/String;Ljava/lang/String;Ljava/lang/String;Ljava/lang/String;Ljava/lang/String;)Landroid/database/Cursor;
        //   175: astore          9
        //   177: ldc2_w          -1
        //   180: lstore          4
        //   182: aload           8
        //   184: astore          11
        //   186: aload           9
        //   188: astore          10
        //   190: aload           9
        //   192: invokeinterface android/database/Cursor.moveToNext:()Z
        //   197: ifeq            699
        //   200: aload           8
        //   202: astore          11
        //   204: aload           9
        //   206: astore          10
        //   208: aload           9
        //   210: iconst_0       
        //   211: invokeinterface android/database/Cursor.getLong:(I)J
        //   216: lstore          6
        //   218: aload           8
        //   220: astore          11
        //   222: aload           9
        //   224: astore          10
        //   226: aload           9
        //   228: iconst_1       
        //   229: invokeinterface android/database/Cursor.getInt:(I)I
        //   234: istore_2       
        //   235: aload           8
        //   237: astore          11
        //   239: aload           9
        //   241: astore          10
        //   243: aload           9
        //   245: iconst_2       
        //   246: invokeinterface android/database/Cursor.getBlob:(I)[B
        //   251: astore          12
        //   253: iload_2        
        //   254: ifne            413
        //   257: aload           8
        //   259: astore          11
        //   261: aload           9
        //   263: astore          10
        //   265: invokestatic    android/os/Parcel.obtain:()Landroid/os/Parcel;
        //   268: astore          14
        //   270: aload           14
        //   272: aload           12
        //   274: iconst_0       
        //   275: aload           12
        //   277: arraylength    
        //   278: invokevirtual   android/os/Parcel.unmarshall:([BII)V
        //   281: aload           14
        //   283: iconst_0       
        //   284: invokevirtual   android/os/Parcel.setDataPosition:(I)V
        //   287: getstatic       com/google/android/gms/measurement/internal/zzad.CREATOR:Landroid/os/Parcelable$Creator;
        //   290: aload           14
        //   292: invokeinterface android/os/Parcelable$Creator.createFromParcel:(Landroid/os/Parcel;)Ljava/lang/Object;
        //   297: checkcast       Lcom/google/android/gms/measurement/internal/zzad;
        //   300: astore          12
        //   302: aload           8
        //   304: astore          11
        //   306: aload           9
        //   308: astore          10
        //   310: aload           14
        //   312: invokevirtual   android/os/Parcel.recycle:()V
        //   315: lload           6
        //   317: lstore          4
        //   319: aload           12
        //   321: ifnull          182
        //   324: aload           8
        //   326: astore          11
        //   328: aload           9
        //   330: astore          10
        //   332: aload           13
        //   334: aload           12
        //   336: invokeinterface java/util/List.add:(Ljava/lang/Object;)Z
        //   341: pop            
        //   342: lload           6
        //   344: lstore          4
        //   346: goto            182
        //   349: astore          12
        //   351: goto            389
        //   354: astore          10
        //   356: aload_0        
        //   357: invokevirtual   com/google/android/gms/measurement/internal/zzco.zzgo:()Lcom/google/android/gms/measurement/internal/zzap;
        //   360: invokevirtual   com/google/android/gms/measurement/internal/zzap.zzjd:()Lcom/google/android/gms/measurement/internal/zzar;
        //   363: ldc_w           "Failed to load event from local database"
        //   366: invokevirtual   com/google/android/gms/measurement/internal/zzar.zzbx:(Ljava/lang/String;)V
        //   369: aload           8
        //   371: astore          11
        //   373: aload           9
        //   375: astore          10
        //   377: aload           14
        //   379: invokevirtual   android/os/Parcel.recycle:()V
        //   382: lload           6
        //   384: lstore          4
        //   386: goto            182
        //   389: aload           8
        //   391: astore          11
        //   393: aload           9
        //   395: astore          10
        //   397: aload           14
        //   399: invokevirtual   android/os/Parcel.recycle:()V
        //   402: aload           8
        //   404: astore          11
        //   406: aload           9
        //   408: astore          10
        //   410: aload           12
        //   412: athrow         
        //   413: iload_2        
        //   414: iconst_1       
        //   415: if_icmpne       542
        //   418: aload           8
        //   420: astore          11
        //   422: aload           9
        //   424: astore          10
        //   426: invokestatic    android/os/Parcel.obtain:()Landroid/os/Parcel;
        //   429: astore          14
        //   431: aload           14
        //   433: aload           12
        //   435: iconst_0       
        //   436: aload           12
        //   438: arraylength    
        //   439: invokevirtual   android/os/Parcel.unmarshall:([BII)V
        //   442: aload           14
        //   444: iconst_0       
        //   445: invokevirtual   android/os/Parcel.setDataPosition:(I)V
        //   448: getstatic       com/google/android/gms/measurement/internal/zzfh.CREATOR:Landroid/os/Parcelable$Creator;
        //   451: aload           14
        //   453: invokeinterface android/os/Parcelable$Creator.createFromParcel:(Landroid/os/Parcel;)Ljava/lang/Object;
        //   458: checkcast       Lcom/google/android/gms/measurement/internal/zzfh;
        //   461: astore          12
        //   463: aload           8
        //   465: astore          11
        //   467: aload           9
        //   469: astore          10
        //   471: aload           14
        //   473: invokevirtual   android/os/Parcel.recycle:()V
        //   476: goto            1212
        //   479: astore          12
        //   481: goto            518
        //   484: astore          10
        //   486: aload_0        
        //   487: invokevirtual   com/google/android/gms/measurement/internal/zzco.zzgo:()Lcom/google/android/gms/measurement/internal/zzap;
        //   490: invokevirtual   com/google/android/gms/measurement/internal/zzap.zzjd:()Lcom/google/android/gms/measurement/internal/zzar;
        //   493: ldc_w           "Failed to load user property from local database"
        //   496: invokevirtual   com/google/android/gms/measurement/internal/zzar.zzbx:(Ljava/lang/String;)V
        //   499: aload           8
        //   501: astore          11
        //   503: aload           9
        //   505: astore          10
        //   507: aload           14
        //   509: invokevirtual   android/os/Parcel.recycle:()V
        //   512: aconst_null    
        //   513: astore          12
        //   515: goto            1212
        //   518: aload           8
        //   520: astore          11
        //   522: aload           9
        //   524: astore          10
        //   526: aload           14
        //   528: invokevirtual   android/os/Parcel.recycle:()V
        //   531: aload           8
        //   533: astore          11
        //   535: aload           9
        //   537: astore          10
        //   539: aload           12
        //   541: athrow         
        //   542: iload_2        
        //   543: iconst_2       
        //   544: if_icmpne       671
        //   547: aload           8
        //   549: astore          11
        //   551: aload           9
        //   553: astore          10
        //   555: invokestatic    android/os/Parcel.obtain:()Landroid/os/Parcel;
        //   558: astore          14
        //   560: aload           14
        //   562: aload           12
        //   564: iconst_0       
        //   565: aload           12
        //   567: arraylength    
        //   568: invokevirtual   android/os/Parcel.unmarshall:([BII)V
        //   571: aload           14
        //   573: iconst_0       
        //   574: invokevirtual   android/os/Parcel.setDataPosition:(I)V
        //   577: getstatic       com/google/android/gms/measurement/internal/zzl.CREATOR:Landroid/os/Parcelable$Creator;
        //   580: aload           14
        //   582: invokeinterface android/os/Parcelable$Creator.createFromParcel:(Landroid/os/Parcel;)Ljava/lang/Object;
        //   587: checkcast       Lcom/google/android/gms/measurement/internal/zzl;
        //   590: astore          12
        //   592: aload           8
        //   594: astore          11
        //   596: aload           9
        //   598: astore          10
        //   600: aload           14
        //   602: invokevirtual   android/os/Parcel.recycle:()V
        //   605: goto            1224
        //   608: astore          12
        //   610: goto            647
        //   613: astore          10
        //   615: aload_0        
        //   616: invokevirtual   com/google/android/gms/measurement/internal/zzco.zzgo:()Lcom/google/android/gms/measurement/internal/zzap;
        //   619: invokevirtual   com/google/android/gms/measurement/internal/zzap.zzjd:()Lcom/google/android/gms/measurement/internal/zzar;
        //   622: ldc_w           "Failed to load user property from local database"
        //   625: invokevirtual   com/google/android/gms/measurement/internal/zzar.zzbx:(Ljava/lang/String;)V
        //   628: aload           8
        //   630: astore          11
        //   632: aload           9
        //   634: astore          10
        //   636: aload           14
        //   638: invokevirtual   android/os/Parcel.recycle:()V
        //   641: aconst_null    
        //   642: astore          12
        //   644: goto            1224
        //   647: aload           8
        //   649: astore          11
        //   651: aload           9
        //   653: astore          10
        //   655: aload           14
        //   657: invokevirtual   android/os/Parcel.recycle:()V
        //   660: aload           8
        //   662: astore          11
        //   664: aload           9
        //   666: astore          10
        //   668: aload           12
        //   670: athrow         
        //   671: aload           8
        //   673: astore          11
        //   675: aload           9
        //   677: astore          10
        //   679: aload_0        
        //   680: invokevirtual   com/google/android/gms/measurement/internal/zzco.zzgo:()Lcom/google/android/gms/measurement/internal/zzap;
        //   683: invokevirtual   com/google/android/gms/measurement/internal/zzap.zzjd:()Lcom/google/android/gms/measurement/internal/zzar;
        //   686: ldc_w           "Unknown record type in local database"
        //   689: invokevirtual   com/google/android/gms/measurement/internal/zzar.zzbx:(Ljava/lang/String;)V
        //   692: lload           6
        //   694: lstore          4
        //   696: goto            182
        //   699: aload           8
        //   701: astore          11
        //   703: aload           9
        //   705: astore          10
        //   707: aload           8
        //   709: ldc             "messages"
        //   711: ldc_w           "rowid <= ?"
        //   714: iconst_1       
        //   715: anewarray       Ljava/lang/String;
        //   718: dup            
        //   719: iconst_0       
        //   720: lload           4
        //   722: invokestatic    java/lang/Long.toString:(J)Ljava/lang/String;
        //   725: aastore        
        //   726: invokevirtual   android/database/sqlite/SQLiteDatabase.delete:(Ljava/lang/String;Ljava/lang/String;[Ljava/lang/String;)I
        //   729: aload           13
        //   731: invokeinterface java/util/List.size:()I
        //   736: if_icmpge       760
        //   739: aload           8
        //   741: astore          11
        //   743: aload           9
        //   745: astore          10
        //   747: aload_0        
        //   748: invokevirtual   com/google/android/gms/measurement/internal/zzco.zzgo:()Lcom/google/android/gms/measurement/internal/zzap;
        //   751: invokevirtual   com/google/android/gms/measurement/internal/zzap.zzjd:()Lcom/google/android/gms/measurement/internal/zzar;
        //   754: ldc_w           "Fewer entries removed from local database than expected"
        //   757: invokevirtual   com/google/android/gms/measurement/internal/zzar.zzbx:(Ljava/lang/String;)V
        //   760: aload           8
        //   762: astore          11
        //   764: aload           9
        //   766: astore          10
        //   768: aload           8
        //   770: invokevirtual   android/database/sqlite/SQLiteDatabase.setTransactionSuccessful:()V
        //   773: aload           8
        //   775: astore          11
        //   777: aload           9
        //   779: astore          10
        //   781: aload           8
        //   783: invokevirtual   android/database/sqlite/SQLiteDatabase.endTransaction:()V
        //   786: aload           9
        //   788: ifnull          798
        //   791: aload           9
        //   793: invokeinterface android/database/Cursor.close:()V
        //   798: aload           8
        //   800: ifnull          808
        //   803: aload           8
        //   805: invokevirtual   android/database/sqlite/SQLiteDatabase.close:()V
        //   808: aload           13
        //   810: areturn        
        //   811: astore          8
        //   813: goto            1172
        //   816: astore          12
        //   818: goto            937
        //   821: astore          10
        //   823: goto            1037
        //   826: astore          10
        //   828: aload           8
        //   830: astore          11
        //   832: aload           9
        //   834: astore          8
        //   836: aload           11
        //   838: astore          9
        //   840: goto            1096
        //   843: astore          8
        //   845: goto            865
        //   848: astore          8
        //   850: goto            874
        //   853: astore          9
        //   855: goto            1034
        //   858: astore          8
        //   860: goto            896
        //   863: astore          8
        //   865: aload           10
        //   867: astore          11
        //   869: goto            923
        //   872: astore          8
        //   874: aload           8
        //   876: astore          12
        //   878: aload           10
        //   880: astore          8
        //   882: goto            934
        //   885: astore          8
        //   887: aload           9
        //   889: astore          8
        //   891: goto            1034
        //   894: astore          8
        //   896: aload           8
        //   898: astore          9
        //   900: aload           10
        //   902: astore          11
        //   904: aconst_null    
        //   905: astore          8
        //   907: aload           9
        //   909: astore          10
        //   911: aload           11
        //   913: astore          9
        //   915: goto            1096
        //   918: astore          8
        //   920: aconst_null    
        //   921: astore          11
        //   923: aconst_null    
        //   924: astore          10
        //   926: goto            1172
        //   929: astore          12
        //   931: aconst_null    
        //   932: astore          8
        //   934: aconst_null    
        //   935: astore          9
        //   937: aload           8
        //   939: ifnull          971
        //   942: aload           8
        //   944: astore          11
        //   946: aload           9
        //   948: astore          10
        //   950: aload           8
        //   952: invokevirtual   android/database/sqlite/SQLiteDatabase.inTransaction:()Z
        //   955: ifeq            971
        //   958: aload           8
        //   960: astore          11
        //   962: aload           9
        //   964: astore          10
        //   966: aload           8
        //   968: invokevirtual   android/database/sqlite/SQLiteDatabase.endTransaction:()V
        //   971: aload           8
        //   973: astore          11
        //   975: aload           9
        //   977: astore          10
        //   979: aload_0        
        //   980: invokevirtual   com/google/android/gms/measurement/internal/zzco.zzgo:()Lcom/google/android/gms/measurement/internal/zzap;
        //   983: invokevirtual   com/google/android/gms/measurement/internal/zzap.zzjd:()Lcom/google/android/gms/measurement/internal/zzar;
        //   986: ldc_w           "Error reading entries from local database"
        //   989: aload           12
        //   991: invokevirtual   com/google/android/gms/measurement/internal/zzar.zzg:(Ljava/lang/String;Ljava/lang/Object;)V
        //   994: aload           8
        //   996: astore          11
        //   998: aload           9
        //  1000: astore          10
        //  1002: aload_0        
        //  1003: iconst_1       
        //  1004: putfield        com/google/android/gms/measurement/internal/zzal.zzalr:Z
        //  1007: aload           9
        //  1009: ifnull          1019
        //  1012: aload           9
        //  1014: invokeinterface android/database/Cursor.close:()V
        //  1019: iload_1        
        //  1020: istore_2       
        //  1021: aload           8
        //  1023: ifnull          1158
        //  1026: goto            1078
        //  1029: astore          8
        //  1031: aconst_null    
        //  1032: astore          8
        //  1034: aconst_null    
        //  1035: astore          9
        //  1037: iload_1        
        //  1038: i2l            
        //  1039: lstore          4
        //  1041: aload           8
        //  1043: astore          11
        //  1045: aload           9
        //  1047: astore          10
        //  1049: lload           4
        //  1051: invokestatic    android/os/SystemClock.sleep:(J)V
        //  1054: iload_1        
        //  1055: bipush          20
        //  1057: iadd           
        //  1058: istore_1       
        //  1059: aload           9
        //  1061: ifnull          1071
        //  1064: aload           9
        //  1066: invokeinterface android/database/Cursor.close:()V
        //  1071: iload_1        
        //  1072: istore_2       
        //  1073: aload           8
        //  1075: ifnull          1158
        //  1078: aload           8
        //  1080: invokevirtual   android/database/sqlite/SQLiteDatabase.close:()V
        //  1083: iload_1        
        //  1084: istore_2       
        //  1085: goto            1158
        //  1088: astore          10
        //  1090: aconst_null    
        //  1091: astore          8
        //  1093: aconst_null    
        //  1094: astore          9
        //  1096: aload           8
        //  1098: astore          12
        //  1100: aload           9
        //  1102: astore          11
        //  1104: aload_0        
        //  1105: invokevirtual   com/google/android/gms/measurement/internal/zzco.zzgo:()Lcom/google/android/gms/measurement/internal/zzap;
        //  1108: invokevirtual   com/google/android/gms/measurement/internal/zzap.zzjd:()Lcom/google/android/gms/measurement/internal/zzar;
        //  1111: ldc_w           "Error reading entries from local database"
        //  1114: aload           10
        //  1116: invokevirtual   com/google/android/gms/measurement/internal/zzar.zzg:(Ljava/lang/String;Ljava/lang/Object;)V
        //  1119: aload           8
        //  1121: astore          12
        //  1123: aload           9
        //  1125: astore          11
        //  1127: aload_0        
        //  1128: iconst_1       
        //  1129: putfield        com/google/android/gms/measurement/internal/zzal.zzalr:Z
        //  1132: aload           8
        //  1134: ifnull          1144
        //  1137: aload           8
        //  1139: invokeinterface android/database/Cursor.close:()V
        //  1144: iload_1        
        //  1145: istore_2       
        //  1146: aload           9
        //  1148: ifnull          1158
        //  1151: aload           9
        //  1153: invokevirtual   android/database/sqlite/SQLiteDatabase.close:()V
        //  1156: iload_1        
        //  1157: istore_2       
        //  1158: iload_3        
        //  1159: iconst_1       
        //  1160: iadd           
        //  1161: istore_3       
        //  1162: iload_2        
        //  1163: istore_1       
        //  1164: goto            48
        //  1167: astore          8
        //  1169: goto            95
        //  1172: aload           10
        //  1174: ifnull          1184
        //  1177: aload           10
        //  1179: invokeinterface android/database/Cursor.close:()V
        //  1184: aload           11
        //  1186: ifnull          1194
        //  1189: aload           11
        //  1191: invokevirtual   android/database/sqlite/SQLiteDatabase.close:()V
        //  1194: aload           8
        //  1196: athrow         
        //  1197: aload_0        
        //  1198: invokevirtual   com/google/android/gms/measurement/internal/zzco.zzgo:()Lcom/google/android/gms/measurement/internal/zzap;
        //  1201: invokevirtual   com/google/android/gms/measurement/internal/zzap.zzjg:()Lcom/google/android/gms/measurement/internal/zzar;
        //  1204: ldc_w           "Failed to read events from database in reasonable time"
        //  1207: invokevirtual   com/google/android/gms/measurement/internal/zzar.zzbx:(Ljava/lang/String;)V
        //  1210: aconst_null    
        //  1211: areturn        
        //  1212: lload           6
        //  1214: lstore          4
        //  1216: aload           12
        //  1218: ifnull          182
        //  1221: goto            324
        //  1224: lload           6
        //  1226: lstore          4
        //  1228: aload           12
        //  1230: ifnull          182
        //  1233: goto            324
        //    Signature:
        //  (I)Ljava/util/List<Lcom/google/android/gms/common/internal/safeparcel/AbstractSafeParcelable;>;
        //    Exceptions:
        //  Try           Handler
        //  Start  End    Start  End    Type                                                                               
        //  -----  -----  -----  -----  -----------------------------------------------------------------------------------
        //  59     65     1088   1096   Landroid/database/sqlite/SQLiteFullException;
        //  59     65     1029   1034   Landroid/database/sqlite/SQLiteDatabaseLockedException;
        //  59     65     929    934    Landroid/database/sqlite/SQLiteException;
        //  59     65     918    923    Any
        //  78     83     118    123    Landroid/database/sqlite/SQLiteFullException;
        //  78     83     885    894    Landroid/database/sqlite/SQLiteDatabaseLockedException;
        //  78     83     102    118    Landroid/database/sqlite/SQLiteException;
        //  78     83     1167   102    Any
        //  123    135    894    896    Landroid/database/sqlite/SQLiteFullException;
        //  123    135    885    894    Landroid/database/sqlite/SQLiteDatabaseLockedException;
        //  123    135    872    874    Landroid/database/sqlite/SQLiteException;
        //  123    135    863    865    Any
        //  139    177    858    863    Landroid/database/sqlite/SQLiteFullException;
        //  139    177    853    858    Landroid/database/sqlite/SQLiteDatabaseLockedException;
        //  139    177    848    853    Landroid/database/sqlite/SQLiteException;
        //  139    177    843    848    Any
        //  190    200    826    843    Landroid/database/sqlite/SQLiteFullException;
        //  190    200    821    826    Landroid/database/sqlite/SQLiteDatabaseLockedException;
        //  190    200    816    821    Landroid/database/sqlite/SQLiteException;
        //  190    200    811    816    Any
        //  208    218    826    843    Landroid/database/sqlite/SQLiteFullException;
        //  208    218    821    826    Landroid/database/sqlite/SQLiteDatabaseLockedException;
        //  208    218    816    821    Landroid/database/sqlite/SQLiteException;
        //  208    218    811    816    Any
        //  226    235    826    843    Landroid/database/sqlite/SQLiteFullException;
        //  226    235    821    826    Landroid/database/sqlite/SQLiteDatabaseLockedException;
        //  226    235    816    821    Landroid/database/sqlite/SQLiteException;
        //  226    235    811    816    Any
        //  243    253    826    843    Landroid/database/sqlite/SQLiteFullException;
        //  243    253    821    826    Landroid/database/sqlite/SQLiteDatabaseLockedException;
        //  243    253    816    821    Landroid/database/sqlite/SQLiteException;
        //  243    253    811    816    Any
        //  265    270    826    843    Landroid/database/sqlite/SQLiteFullException;
        //  265    270    821    826    Landroid/database/sqlite/SQLiteDatabaseLockedException;
        //  265    270    816    821    Landroid/database/sqlite/SQLiteException;
        //  265    270    811    816    Any
        //  270    302    354    389    Lcom/google/android/gms/common/internal/safeparcel/SafeParcelReader$ParseException;
        //  270    302    349    413    Any
        //  310    315    826    843    Landroid/database/sqlite/SQLiteFullException;
        //  310    315    821    826    Landroid/database/sqlite/SQLiteDatabaseLockedException;
        //  310    315    816    821    Landroid/database/sqlite/SQLiteException;
        //  310    315    811    816    Any
        //  332    342    826    843    Landroid/database/sqlite/SQLiteFullException;
        //  332    342    821    826    Landroid/database/sqlite/SQLiteDatabaseLockedException;
        //  332    342    816    821    Landroid/database/sqlite/SQLiteException;
        //  332    342    811    816    Any
        //  356    369    349    413    Any
        //  377    382    826    843    Landroid/database/sqlite/SQLiteFullException;
        //  377    382    821    826    Landroid/database/sqlite/SQLiteDatabaseLockedException;
        //  377    382    816    821    Landroid/database/sqlite/SQLiteException;
        //  377    382    811    816    Any
        //  397    402    826    843    Landroid/database/sqlite/SQLiteFullException;
        //  397    402    821    826    Landroid/database/sqlite/SQLiteDatabaseLockedException;
        //  397    402    816    821    Landroid/database/sqlite/SQLiteException;
        //  397    402    811    816    Any
        //  410    413    826    843    Landroid/database/sqlite/SQLiteFullException;
        //  410    413    821    826    Landroid/database/sqlite/SQLiteDatabaseLockedException;
        //  410    413    816    821    Landroid/database/sqlite/SQLiteException;
        //  410    413    811    816    Any
        //  426    431    826    843    Landroid/database/sqlite/SQLiteFullException;
        //  426    431    821    826    Landroid/database/sqlite/SQLiteDatabaseLockedException;
        //  426    431    816    821    Landroid/database/sqlite/SQLiteException;
        //  426    431    811    816    Any
        //  431    463    484    518    Lcom/google/android/gms/common/internal/safeparcel/SafeParcelReader$ParseException;
        //  431    463    479    542    Any
        //  471    476    826    843    Landroid/database/sqlite/SQLiteFullException;
        //  471    476    821    826    Landroid/database/sqlite/SQLiteDatabaseLockedException;
        //  471    476    816    821    Landroid/database/sqlite/SQLiteException;
        //  471    476    811    816    Any
        //  486    499    479    542    Any
        //  507    512    826    843    Landroid/database/sqlite/SQLiteFullException;
        //  507    512    821    826    Landroid/database/sqlite/SQLiteDatabaseLockedException;
        //  507    512    816    821    Landroid/database/sqlite/SQLiteException;
        //  507    512    811    816    Any
        //  526    531    826    843    Landroid/database/sqlite/SQLiteFullException;
        //  526    531    821    826    Landroid/database/sqlite/SQLiteDatabaseLockedException;
        //  526    531    816    821    Landroid/database/sqlite/SQLiteException;
        //  526    531    811    816    Any
        //  539    542    826    843    Landroid/database/sqlite/SQLiteFullException;
        //  539    542    821    826    Landroid/database/sqlite/SQLiteDatabaseLockedException;
        //  539    542    816    821    Landroid/database/sqlite/SQLiteException;
        //  539    542    811    816    Any
        //  555    560    826    843    Landroid/database/sqlite/SQLiteFullException;
        //  555    560    821    826    Landroid/database/sqlite/SQLiteDatabaseLockedException;
        //  555    560    816    821    Landroid/database/sqlite/SQLiteException;
        //  555    560    811    816    Any
        //  560    592    613    647    Lcom/google/android/gms/common/internal/safeparcel/SafeParcelReader$ParseException;
        //  560    592    608    671    Any
        //  600    605    826    843    Landroid/database/sqlite/SQLiteFullException;
        //  600    605    821    826    Landroid/database/sqlite/SQLiteDatabaseLockedException;
        //  600    605    816    821    Landroid/database/sqlite/SQLiteException;
        //  600    605    811    816    Any
        //  615    628    608    671    Any
        //  636    641    826    843    Landroid/database/sqlite/SQLiteFullException;
        //  636    641    821    826    Landroid/database/sqlite/SQLiteDatabaseLockedException;
        //  636    641    816    821    Landroid/database/sqlite/SQLiteException;
        //  636    641    811    816    Any
        //  655    660    826    843    Landroid/database/sqlite/SQLiteFullException;
        //  655    660    821    826    Landroid/database/sqlite/SQLiteDatabaseLockedException;
        //  655    660    816    821    Landroid/database/sqlite/SQLiteException;
        //  655    660    811    816    Any
        //  668    671    826    843    Landroid/database/sqlite/SQLiteFullException;
        //  668    671    821    826    Landroid/database/sqlite/SQLiteDatabaseLockedException;
        //  668    671    816    821    Landroid/database/sqlite/SQLiteException;
        //  668    671    811    816    Any
        //  679    692    826    843    Landroid/database/sqlite/SQLiteFullException;
        //  679    692    821    826    Landroid/database/sqlite/SQLiteDatabaseLockedException;
        //  679    692    816    821    Landroid/database/sqlite/SQLiteException;
        //  679    692    811    816    Any
        //  707    739    826    843    Landroid/database/sqlite/SQLiteFullException;
        //  707    739    821    826    Landroid/database/sqlite/SQLiteDatabaseLockedException;
        //  707    739    816    821    Landroid/database/sqlite/SQLiteException;
        //  707    739    811    816    Any
        //  747    760    826    843    Landroid/database/sqlite/SQLiteFullException;
        //  747    760    821    826    Landroid/database/sqlite/SQLiteDatabaseLockedException;
        //  747    760    816    821    Landroid/database/sqlite/SQLiteException;
        //  747    760    811    816    Any
        //  768    773    826    843    Landroid/database/sqlite/SQLiteFullException;
        //  768    773    821    826    Landroid/database/sqlite/SQLiteDatabaseLockedException;
        //  768    773    816    821    Landroid/database/sqlite/SQLiteException;
        //  768    773    811    816    Any
        //  781    786    826    843    Landroid/database/sqlite/SQLiteFullException;
        //  781    786    821    826    Landroid/database/sqlite/SQLiteDatabaseLockedException;
        //  781    786    816    821    Landroid/database/sqlite/SQLiteException;
        //  781    786    811    816    Any
        //  950    958    811    816    Any
        //  966    971    811    816    Any
        //  979    994    811    816    Any
        //  1002   1007   811    816    Any
        //  1049   1054   811    816    Any
        //  1104   1119   1167   102    Any
        //  1127   1132   1167   102    Any
        // 
        // The error that occurred was:
        // 
        // java.lang.IllegalStateException: Expression is linked from several locations: Label_0093:
        //     at com.strobel.decompiler.ast.Error.expressionLinkedFromMultipleLocations(Error.java:27)
        //     at com.strobel.decompiler.ast.AstOptimizer.mergeDisparateObjectInitializations(AstOptimizer.java:2596)
        //     at com.strobel.decompiler.ast.AstOptimizer.optimize(AstOptimizer.java:235)
        //     at com.strobel.decompiler.ast.AstOptimizer.optimize(AstOptimizer.java:42)
        //     at com.strobel.decompiler.languages.java.ast.AstMethodBodyBuilder.createMethodBody(AstMethodBodyBuilder.java:214)
        //     at com.strobel.decompiler.languages.java.ast.AstMethodBodyBuilder.createMethodBody(AstMethodBodyBuilder.java:99)
        //     at com.strobel.decompiler.languages.java.ast.AstBuilder.createMethodBody(AstBuilder.java:782)
        //     at com.strobel.decompiler.languages.java.ast.AstBuilder.createMethod(AstBuilder.java:675)
        //     at com.strobel.decompiler.languages.java.ast.AstBuilder.addTypeMembers(AstBuilder.java:552)
        //     at com.strobel.decompiler.languages.java.ast.AstBuilder.createTypeCore(AstBuilder.java:519)
        //     at com.strobel.decompiler.languages.java.ast.AstBuilder.createTypeNoCache(AstBuilder.java:161)
        //     at com.strobel.decompiler.languages.java.ast.AstBuilder.createType(AstBuilder.java:150)
        //     at com.strobel.decompiler.languages.java.ast.AstBuilder.addType(AstBuilder.java:125)
        //     at com.strobel.decompiler.languages.java.JavaLanguage.buildAst(JavaLanguage.java:71)
        //     at com.strobel.decompiler.languages.java.JavaLanguage.decompileType(JavaLanguage.java:59)
        //     at us.deathmarine.luyten.FileSaver.doSaveJarDecompiled(FileSaver.java:192)
        //     at us.deathmarine.luyten.FileSaver.access$300(FileSaver.java:45)
        //     at us.deathmarine.luyten.FileSaver$4.run(FileSaver.java:112)
        //     at java.lang.Thread.run(Unknown Source)
        // 
        throw new IllegalStateException("An error occurred while decompiling this method.");
    }
}
