package com.google.android.gms.measurement.internal;

import java.util.concurrent.atomic.*;

final class zzdu implements Runnable
{
    private final /* synthetic */ zzh zzaqn;
    private final /* synthetic */ zzdr zzasg;
    private final /* synthetic */ AtomicReference zzash;
    
    zzdu(final zzdr zzasg, final AtomicReference zzash, final zzh zzaqn) {
        this.zzasg = zzasg;
        this.zzash = zzash;
        this.zzaqn = zzaqn;
    }
    
    @Override
    public final void run() {
        // 
        // This method could not be decompiled.
        // 
        // Original Bytecode:
        // 
        //     1: getfield        com/google/android/gms/measurement/internal/zzdu.zzash:Ljava/util/concurrent/atomic/AtomicReference;
        //     4: astore_2       
        //     5: aload_2        
        //     6: monitorenter   
        //     7: aload_0        
        //     8: getfield        com/google/android/gms/measurement/internal/zzdu.zzasg:Lcom/google/android/gms/measurement/internal/zzdr;
        //    11: invokestatic    com/google/android/gms/measurement/internal/zzdr.zzd:(Lcom/google/android/gms/measurement/internal/zzdr;)Lcom/google/android/gms/measurement/internal/zzag;
        //    14: astore_1       
        //    15: aload_1        
        //    16: ifnonnull       44
        //    19: aload_0        
        //    20: getfield        com/google/android/gms/measurement/internal/zzdu.zzasg:Lcom/google/android/gms/measurement/internal/zzdr;
        //    23: invokevirtual   com/google/android/gms/measurement/internal/zzco.zzgo:()Lcom/google/android/gms/measurement/internal/zzap;
        //    26: invokevirtual   com/google/android/gms/measurement/internal/zzap.zzjd:()Lcom/google/android/gms/measurement/internal/zzar;
        //    29: ldc             "Failed to get app instance id"
        //    31: invokevirtual   com/google/android/gms/measurement/internal/zzar.zzbx:(Ljava/lang/String;)V
        //    34: aload_0        
        //    35: getfield        com/google/android/gms/measurement/internal/zzdu.zzash:Ljava/util/concurrent/atomic/AtomicReference;
        //    38: invokevirtual   java/lang/Object.notify:()V
        //    41: aload_2        
        //    42: monitorexit    
        //    43: return         
        //    44: aload_0        
        //    45: getfield        com/google/android/gms/measurement/internal/zzdu.zzash:Ljava/util/concurrent/atomic/AtomicReference;
        //    48: aload_1        
        //    49: aload_0        
        //    50: getfield        com/google/android/gms/measurement/internal/zzdu.zzaqn:Lcom/google/android/gms/measurement/internal/zzh;
        //    53: invokeinterface com/google/android/gms/measurement/internal/zzag.zzc:(Lcom/google/android/gms/measurement/internal/zzh;)Ljava/lang/String;
        //    58: invokevirtual   java/util/concurrent/atomic/AtomicReference.set:(Ljava/lang/Object;)V
        //    61: aload_0        
        //    62: getfield        com/google/android/gms/measurement/internal/zzdu.zzash:Ljava/util/concurrent/atomic/AtomicReference;
        //    65: invokevirtual   java/util/concurrent/atomic/AtomicReference.get:()Ljava/lang/Object;
        //    68: checkcast       Ljava/lang/String;
        //    71: astore_1       
        //    72: aload_1        
        //    73: ifnull          101
        //    76: aload_0        
        //    77: getfield        com/google/android/gms/measurement/internal/zzdu.zzasg:Lcom/google/android/gms/measurement/internal/zzdr;
        //    80: invokevirtual   com/google/android/gms/measurement/internal/zze.zzge:()Lcom/google/android/gms/measurement/internal/zzcs;
        //    83: aload_1        
        //    84: invokevirtual   com/google/android/gms/measurement/internal/zzcs.zzcm:(Ljava/lang/String;)V
        //    87: aload_0        
        //    88: getfield        com/google/android/gms/measurement/internal/zzdu.zzasg:Lcom/google/android/gms/measurement/internal/zzdr;
        //    91: invokevirtual   com/google/android/gms/measurement/internal/zzco.zzgp:()Lcom/google/android/gms/measurement/internal/zzba;
        //    94: getfield        com/google/android/gms/measurement/internal/zzba.zzanl:Lcom/google/android/gms/measurement/internal/zzbf;
        //    97: aload_1        
        //    98: invokevirtual   com/google/android/gms/measurement/internal/zzbf.zzcc:(Ljava/lang/String;)V
        //   101: aload_0        
        //   102: getfield        com/google/android/gms/measurement/internal/zzdu.zzasg:Lcom/google/android/gms/measurement/internal/zzdr;
        //   105: invokestatic    com/google/android/gms/measurement/internal/zzdr.zze:(Lcom/google/android/gms/measurement/internal/zzdr;)V
        //   108: aload_0        
        //   109: getfield        com/google/android/gms/measurement/internal/zzdu.zzash:Ljava/util/concurrent/atomic/AtomicReference;
        //   112: astore_1       
        //   113: aload_1        
        //   114: invokevirtual   java/lang/Object.notify:()V
        //   117: goto            149
        //   120: astore_1       
        //   121: goto            152
        //   124: astore_1       
        //   125: aload_0        
        //   126: getfield        com/google/android/gms/measurement/internal/zzdu.zzasg:Lcom/google/android/gms/measurement/internal/zzdr;
        //   129: invokevirtual   com/google/android/gms/measurement/internal/zzco.zzgo:()Lcom/google/android/gms/measurement/internal/zzap;
        //   132: invokevirtual   com/google/android/gms/measurement/internal/zzap.zzjd:()Lcom/google/android/gms/measurement/internal/zzar;
        //   135: ldc             "Failed to get app instance id"
        //   137: aload_1        
        //   138: invokevirtual   com/google/android/gms/measurement/internal/zzar.zzg:(Ljava/lang/String;Ljava/lang/Object;)V
        //   141: aload_0        
        //   142: getfield        com/google/android/gms/measurement/internal/zzdu.zzash:Ljava/util/concurrent/atomic/AtomicReference;
        //   145: astore_1       
        //   146: goto            113
        //   149: aload_2        
        //   150: monitorexit    
        //   151: return         
        //   152: aload_0        
        //   153: getfield        com/google/android/gms/measurement/internal/zzdu.zzash:Ljava/util/concurrent/atomic/AtomicReference;
        //   156: invokevirtual   java/lang/Object.notify:()V
        //   159: aload_1        
        //   160: athrow         
        //   161: astore_1       
        //   162: aload_2        
        //   163: monitorexit    
        //   164: aload_1        
        //   165: athrow         
        //    Exceptions:
        //  Try           Handler
        //  Start  End    Start  End    Type                        
        //  -----  -----  -----  -----  ----------------------------
        //  7      15     124    149    Landroid/os/RemoteException;
        //  7      15     120    124    Any
        //  19     34     124    149    Landroid/os/RemoteException;
        //  19     34     120    124    Any
        //  34     43     161    166    Any
        //  44     72     124    149    Landroid/os/RemoteException;
        //  44     72     120    124    Any
        //  76     101    124    149    Landroid/os/RemoteException;
        //  76     101    120    124    Any
        //  101    108    124    149    Landroid/os/RemoteException;
        //  101    108    120    124    Any
        //  108    113    161    166    Any
        //  113    117    161    166    Any
        //  125    141    120    124    Any
        //  141    146    161    166    Any
        //  149    151    161    166    Any
        //  152    161    161    166    Any
        //  162    164    161    166    Any
        // 
        // The error that occurred was:
        // 
        // java.lang.IllegalStateException: Expression is linked from several locations: Label_0044:
        //     at com.strobel.decompiler.ast.Error.expressionLinkedFromMultipleLocations(Error.java:27)
        //     at com.strobel.decompiler.ast.AstOptimizer.mergeDisparateObjectInitializations(AstOptimizer.java:2596)
        //     at com.strobel.decompiler.ast.AstOptimizer.optimize(AstOptimizer.java:235)
        //     at com.strobel.decompiler.ast.AstOptimizer.optimize(AstOptimizer.java:42)
        //     at com.strobel.decompiler.languages.java.ast.AstMethodBodyBuilder.createMethodBody(AstMethodBodyBuilder.java:214)
        //     at com.strobel.decompiler.languages.java.ast.AstMethodBodyBuilder.createMethodBody(AstMethodBodyBuilder.java:99)
        //     at com.strobel.decompiler.languages.java.ast.AstBuilder.createMethodBody(AstBuilder.java:782)
        //     at com.strobel.decompiler.languages.java.ast.AstBuilder.createMethod(AstBuilder.java:675)
        //     at com.strobel.decompiler.languages.java.ast.AstBuilder.addTypeMembers(AstBuilder.java:552)
        //     at com.strobel.decompiler.languages.java.ast.AstBuilder.createTypeCore(AstBuilder.java:519)
        //     at com.strobel.decompiler.languages.java.ast.AstBuilder.createTypeNoCache(AstBuilder.java:161)
        //     at com.strobel.decompiler.languages.java.ast.AstBuilder.createType(AstBuilder.java:150)
        //     at com.strobel.decompiler.languages.java.ast.AstBuilder.addType(AstBuilder.java:125)
        //     at com.strobel.decompiler.languages.java.JavaLanguage.buildAst(JavaLanguage.java:71)
        //     at com.strobel.decompiler.languages.java.JavaLanguage.decompileType(JavaLanguage.java:59)
        //     at us.deathmarine.luyten.FileSaver.doSaveJarDecompiled(FileSaver.java:192)
        //     at us.deathmarine.luyten.FileSaver.access$300(FileSaver.java:45)
        //     at us.deathmarine.luyten.FileSaver$4.run(FileSaver.java:112)
        //     at java.lang.Thread.run(Unknown Source)
        // 
        throw new IllegalStateException("An error occurred while decompiling this method.");
    }
}
