package com.google.android.gms.measurement.internal;

import java.util.concurrent.atomic.*;

final class zzeb implements Runnable
{
    private final /* synthetic */ String zzaeh;
    private final /* synthetic */ String zzaeo;
    private final /* synthetic */ zzh zzaqn;
    private final /* synthetic */ String zzaqq;
    private final /* synthetic */ zzdr zzasg;
    private final /* synthetic */ AtomicReference zzash;
    
    zzeb(final zzdr zzasg, final AtomicReference zzash, final String zzaqq, final String zzaeh, final String zzaeo, final zzh zzaqn) {
        this.zzasg = zzasg;
        this.zzash = zzash;
        this.zzaqq = zzaqq;
        this.zzaeh = zzaeh;
        this.zzaeo = zzaeo;
        this.zzaqn = zzaqn;
    }
    
    @Override
    public final void run() {
        // 
        // This method could not be decompiled.
        // 
        // Original Bytecode:
        // 
        //     1: getfield        com/google/android/gms/measurement/internal/zzeb.zzash:Ljava/util/concurrent/atomic/AtomicReference;
        //     4: astore_3       
        //     5: aload_3        
        //     6: monitorenter   
        //     7: aload_0        
        //     8: getfield        com/google/android/gms/measurement/internal/zzeb.zzasg:Lcom/google/android/gms/measurement/internal/zzdr;
        //    11: invokestatic    com/google/android/gms/measurement/internal/zzdr.zzd:(Lcom/google/android/gms/measurement/internal/zzdr;)Lcom/google/android/gms/measurement/internal/zzag;
        //    14: astore_1       
        //    15: aload_1        
        //    16: ifnonnull       69
        //    19: aload_0        
        //    20: getfield        com/google/android/gms/measurement/internal/zzeb.zzasg:Lcom/google/android/gms/measurement/internal/zzdr;
        //    23: invokevirtual   com/google/android/gms/measurement/internal/zzco.zzgo:()Lcom/google/android/gms/measurement/internal/zzap;
        //    26: invokevirtual   com/google/android/gms/measurement/internal/zzap.zzjd:()Lcom/google/android/gms/measurement/internal/zzar;
        //    29: ldc             "Failed to get conditional properties"
        //    31: aload_0        
        //    32: getfield        com/google/android/gms/measurement/internal/zzeb.zzaqq:Ljava/lang/String;
        //    35: invokestatic    com/google/android/gms/measurement/internal/zzap.zzbv:(Ljava/lang/String;)Ljava/lang/Object;
        //    38: aload_0        
        //    39: getfield        com/google/android/gms/measurement/internal/zzeb.zzaeh:Ljava/lang/String;
        //    42: aload_0        
        //    43: getfield        com/google/android/gms/measurement/internal/zzeb.zzaeo:Ljava/lang/String;
        //    46: invokevirtual   com/google/android/gms/measurement/internal/zzar.zzd:(Ljava/lang/String;Ljava/lang/Object;Ljava/lang/Object;Ljava/lang/Object;)V
        //    49: aload_0        
        //    50: getfield        com/google/android/gms/measurement/internal/zzeb.zzash:Ljava/util/concurrent/atomic/AtomicReference;
        //    53: invokestatic    java/util/Collections.emptyList:()Ljava/util/List;
        //    56: invokevirtual   java/util/concurrent/atomic/AtomicReference.set:(Ljava/lang/Object;)V
        //    59: aload_0        
        //    60: getfield        com/google/android/gms/measurement/internal/zzeb.zzash:Ljava/util/concurrent/atomic/AtomicReference;
        //    63: invokevirtual   java/lang/Object.notify:()V
        //    66: aload_3        
        //    67: monitorexit    
        //    68: return         
        //    69: aload_0        
        //    70: getfield        com/google/android/gms/measurement/internal/zzeb.zzaqq:Ljava/lang/String;
        //    73: invokestatic    android/text/TextUtils.isEmpty:(Ljava/lang/CharSequence;)Z
        //    76: ifeq            111
        //    79: aload_0        
        //    80: getfield        com/google/android/gms/measurement/internal/zzeb.zzash:Ljava/util/concurrent/atomic/AtomicReference;
        //    83: astore_2       
        //    84: aload_1        
        //    85: aload_0        
        //    86: getfield        com/google/android/gms/measurement/internal/zzeb.zzaeh:Ljava/lang/String;
        //    89: aload_0        
        //    90: getfield        com/google/android/gms/measurement/internal/zzeb.zzaeo:Ljava/lang/String;
        //    93: aload_0        
        //    94: getfield        com/google/android/gms/measurement/internal/zzeb.zzaqn:Lcom/google/android/gms/measurement/internal/zzh;
        //    97: invokeinterface com/google/android/gms/measurement/internal/zzag.zza:(Ljava/lang/String;Ljava/lang/String;Lcom/google/android/gms/measurement/internal/zzh;)Ljava/util/List;
        //   102: astore_1       
        //   103: aload_2        
        //   104: aload_1        
        //   105: invokevirtual   java/util/concurrent/atomic/AtomicReference.set:(Ljava/lang/Object;)V
        //   108: goto            138
        //   111: aload_0        
        //   112: getfield        com/google/android/gms/measurement/internal/zzeb.zzash:Ljava/util/concurrent/atomic/AtomicReference;
        //   115: astore_2       
        //   116: aload_1        
        //   117: aload_0        
        //   118: getfield        com/google/android/gms/measurement/internal/zzeb.zzaqq:Ljava/lang/String;
        //   121: aload_0        
        //   122: getfield        com/google/android/gms/measurement/internal/zzeb.zzaeh:Ljava/lang/String;
        //   125: aload_0        
        //   126: getfield        com/google/android/gms/measurement/internal/zzeb.zzaeo:Ljava/lang/String;
        //   129: invokeinterface com/google/android/gms/measurement/internal/zzag.zze:(Ljava/lang/String;Ljava/lang/String;Ljava/lang/String;)Ljava/util/List;
        //   134: astore_1       
        //   135: goto            103
        //   138: aload_0        
        //   139: getfield        com/google/android/gms/measurement/internal/zzeb.zzasg:Lcom/google/android/gms/measurement/internal/zzdr;
        //   142: invokestatic    com/google/android/gms/measurement/internal/zzdr.zze:(Lcom/google/android/gms/measurement/internal/zzdr;)V
        //   145: aload_0        
        //   146: getfield        com/google/android/gms/measurement/internal/zzeb.zzash:Ljava/util/concurrent/atomic/AtomicReference;
        //   149: astore_1       
        //   150: aload_1        
        //   151: invokevirtual   java/lang/Object.notify:()V
        //   154: goto            207
        //   157: astore_1       
        //   158: goto            210
        //   161: astore_1       
        //   162: aload_0        
        //   163: getfield        com/google/android/gms/measurement/internal/zzeb.zzasg:Lcom/google/android/gms/measurement/internal/zzdr;
        //   166: invokevirtual   com/google/android/gms/measurement/internal/zzco.zzgo:()Lcom/google/android/gms/measurement/internal/zzap;
        //   169: invokevirtual   com/google/android/gms/measurement/internal/zzap.zzjd:()Lcom/google/android/gms/measurement/internal/zzar;
        //   172: ldc             "Failed to get conditional properties"
        //   174: aload_0        
        //   175: getfield        com/google/android/gms/measurement/internal/zzeb.zzaqq:Ljava/lang/String;
        //   178: invokestatic    com/google/android/gms/measurement/internal/zzap.zzbv:(Ljava/lang/String;)Ljava/lang/Object;
        //   181: aload_0        
        //   182: getfield        com/google/android/gms/measurement/internal/zzeb.zzaeh:Ljava/lang/String;
        //   185: aload_1        
        //   186: invokevirtual   com/google/android/gms/measurement/internal/zzar.zzd:(Ljava/lang/String;Ljava/lang/Object;Ljava/lang/Object;Ljava/lang/Object;)V
        //   189: aload_0        
        //   190: getfield        com/google/android/gms/measurement/internal/zzeb.zzash:Ljava/util/concurrent/atomic/AtomicReference;
        //   193: invokestatic    java/util/Collections.emptyList:()Ljava/util/List;
        //   196: invokevirtual   java/util/concurrent/atomic/AtomicReference.set:(Ljava/lang/Object;)V
        //   199: aload_0        
        //   200: getfield        com/google/android/gms/measurement/internal/zzeb.zzash:Ljava/util/concurrent/atomic/AtomicReference;
        //   203: astore_1       
        //   204: goto            150
        //   207: aload_3        
        //   208: monitorexit    
        //   209: return         
        //   210: aload_0        
        //   211: getfield        com/google/android/gms/measurement/internal/zzeb.zzash:Ljava/util/concurrent/atomic/AtomicReference;
        //   214: invokevirtual   java/lang/Object.notify:()V
        //   217: aload_1        
        //   218: athrow         
        //   219: astore_1       
        //   220: aload_3        
        //   221: monitorexit    
        //   222: aload_1        
        //   223: athrow         
        //    Exceptions:
        //  Try           Handler
        //  Start  End    Start  End    Type                        
        //  -----  -----  -----  -----  ----------------------------
        //  7      15     161    207    Landroid/os/RemoteException;
        //  7      15     157    161    Any
        //  19     59     161    207    Landroid/os/RemoteException;
        //  19     59     157    161    Any
        //  59     68     219    224    Any
        //  69     103    161    207    Landroid/os/RemoteException;
        //  69     103    157    161    Any
        //  103    108    161    207    Landroid/os/RemoteException;
        //  103    108    157    161    Any
        //  111    135    161    207    Landroid/os/RemoteException;
        //  111    135    157    161    Any
        //  138    145    161    207    Landroid/os/RemoteException;
        //  138    145    157    161    Any
        //  145    150    219    224    Any
        //  150    154    219    224    Any
        //  162    199    157    161    Any
        //  199    204    219    224    Any
        //  207    209    219    224    Any
        //  210    219    219    224    Any
        //  220    222    219    224    Any
        // 
        // The error that occurred was:
        // 
        // java.lang.IllegalStateException: Expression is linked from several locations: Label_0069:
        //     at com.strobel.decompiler.ast.Error.expressionLinkedFromMultipleLocations(Error.java:27)
        //     at com.strobel.decompiler.ast.AstOptimizer.mergeDisparateObjectInitializations(AstOptimizer.java:2596)
        //     at com.strobel.decompiler.ast.AstOptimizer.optimize(AstOptimizer.java:235)
        //     at com.strobel.decompiler.ast.AstOptimizer.optimize(AstOptimizer.java:42)
        //     at com.strobel.decompiler.languages.java.ast.AstMethodBodyBuilder.createMethodBody(AstMethodBodyBuilder.java:214)
        //     at com.strobel.decompiler.languages.java.ast.AstMethodBodyBuilder.createMethodBody(AstMethodBodyBuilder.java:99)
        //     at com.strobel.decompiler.languages.java.ast.AstBuilder.createMethodBody(AstBuilder.java:782)
        //     at com.strobel.decompiler.languages.java.ast.AstBuilder.createMethod(AstBuilder.java:675)
        //     at com.strobel.decompiler.languages.java.ast.AstBuilder.addTypeMembers(AstBuilder.java:552)
        //     at com.strobel.decompiler.languages.java.ast.AstBuilder.createTypeCore(AstBuilder.java:519)
        //     at com.strobel.decompiler.languages.java.ast.AstBuilder.createTypeNoCache(AstBuilder.java:161)
        //     at com.strobel.decompiler.languages.java.ast.AstBuilder.createType(AstBuilder.java:150)
        //     at com.strobel.decompiler.languages.java.ast.AstBuilder.addType(AstBuilder.java:125)
        //     at com.strobel.decompiler.languages.java.JavaLanguage.buildAst(JavaLanguage.java:71)
        //     at com.strobel.decompiler.languages.java.JavaLanguage.decompileType(JavaLanguage.java:59)
        //     at us.deathmarine.luyten.FileSaver.doSaveJarDecompiled(FileSaver.java:192)
        //     at us.deathmarine.luyten.FileSaver.access$300(FileSaver.java:45)
        //     at us.deathmarine.luyten.FileSaver$4.run(FileSaver.java:112)
        //     at java.lang.Thread.run(Unknown Source)
        // 
        throw new IllegalStateException("An error occurred while decompiling this method.");
    }
}
